temscale/__init__.py
temscale/temscale.py
temscale-1.1.1.dist-info/METADATA
temscale-1.1.1.dist-info/WHEEL
temscale-1.1.1.dist-info/licenses/LICENSE
temscale-1.1.1.dist-info/RECORD
