Metadata-Version: 2.3
Name: temscale
Version: 1.1.1
Summary: library for working with temperature
Project-URL: Homepage, https://github.com/BRamil1/Temscale-py
Project-URL: Issues, https://github.com/BRamil1/Temscale-py/issues
Author-email: Qulowg <qulowg@gmail.com>
License-File: LICENSE
Classifier: License :: OSI Approved :: MIT License
Classifier: Operating System :: OS Independent
Classifier: Programming Language :: Python :: 3
Requires-Python: >=3.10
